dicompylercore/__init__.py
dicompylercore/config.py
dicompylercore/dicomparser.py
dicompylercore/dose.py
dicompylercore/dvh.py
dicompylercore/dvhcalc.py
dicompylercore/matplotlibshow2.py
dicompylercore/util.py
dicompyler_core-0.5.6.dist-info/AUTHORS.rst
dicompyler_core-0.5.6.dist-info/LICENSE
dicompyler_core-0.5.6.dist-info/METADATA
dicompyler_core-0.5.6.dist-info/WHEEL
dicompyler_core-0.5.6.dist-info/top_level.txt
dicompyler_core-0.5.6.dist-info/RECORD
