Metadata-Version: 2.1
Name: dicompyler-core
Version: 0.5.6
Summary: A library of core radiation therapy modules for DICOM / DICOM RT used by dicompyler
Home-page: https://github.com/dicompyler/dicompyler-core
Author: Aditya Panchal
Author-email: apanchal@bastula.org
License: BSD License
Keywords: dicompyler-core,dicompylercore,dicompyler
Classifier: Development Status :: 4 - Beta
Classifier: Intended Audience :: Developers
Classifier: Intended Audience :: Healthcare Industry
Classifier: Intended Audience :: Science/Research
Classifier: License :: OSI Approved :: BSD License
Classifier: Natural Language :: English
Classifier: Programming Language :: Python :: 3
Classifier: Programming Language :: Python :: 3.7
Classifier: Programming Language :: Python :: 3.8
Classifier: Programming Language :: Python :: 3.9
Classifier: Programming Language :: Python :: 3.10
Classifier: Topic :: Scientific/Engineering :: Medical Science Apps.
Classifier: Topic :: Scientific/Engineering :: Physics
Provides-Extra: image
Provides-Extra: dvhinterpolation
Provides-Extra: volume
Provides-Extra: doseinterpolation
License-File: LICENSE
License-File: AUTHORS.rst
